labelmods/converters/README.md
labelmods/converters/__init__.py
labelmods/converters/coco.py
labelmods/converters/labelbox_converter.py
labelmods/converters/pascal_voc.py
labelmods/converters/yolo.py
labelmods/tests/unit/test_test.py
labelmods-0.0.10.dist-info/METADATA
labelmods-0.0.10.dist-info/WHEEL
labelmods-0.0.10.dist-info/entry_points.txt
labelmods-0.0.10.dist-info/licenses/LICENSE
labelmods-0.0.10.dist-info/RECORD
